avirtech_statistic_generator/__init__.py
avirtech_statistic_generator/avirtech_statistic_generator.py
avirtech_statistic_generator-0.0.3.dist-info/METADATA
avirtech_statistic_generator-0.0.3.dist-info/WHEEL
avirtech_statistic_generator-0.0.3.dist-info/top_level.txt
avirtech_statistic_generator-0.0.3.dist-info/RECORD
