Metadata-Version: 2.1
Name: avirtech-statistic-generator
Version: 0.0.3
Summary: Avirtech Python Library to automize statistic result for outering boundary
Home-page: https://github.com/danibablas
Author: Dani Bablas
Author-email: danibablas@gmail.com
License: MIT
Platform: UNKNOWN
Classifier: Intended Audience :: Developers
Classifier: License :: OSI Approved :: MIT License
Classifier: Programming Language :: Python
Classifier: Programming Language :: Python :: 3
Classifier: Programming Language :: Python :: 3.6
Classifier: Programming Language :: Python :: 3.7
Classifier: Programming Language :: Python :: 3.8
Classifier: Programming Language :: Python :: 3.9
Classifier: Operating System :: OS Independent
Requires-Dist: simpledbf
